bomper/Main.py
bomper/__init__.py
bomper-0.0.1.dist-info/METADATA
bomper-0.0.1.dist-info/WHEEL
bomper-0.0.1.dist-info/top_level.txt
bomper-0.0.1.dist-info/RECORD
