Metadata-Version: 2.1
Name: bomper
Version: 0.0.1
Summary: Spam Anything Anywhere You Want :)
Home-page: UNKNOWN
Author: DrMowz
Author-email: <drmowz8585@gmail.com>
License: UNKNOWN
Keywords: python
Platform: UNKNOWN
Classifier: Development Status :: 1 - Planning
Classifier: Intended Audience :: Developers
Classifier: Programming Language :: Python :: 3
Classifier: Operating System :: Unix
Classifier: Operating System :: MacOS :: MacOS X
Classifier: Operating System :: Microsoft :: Windows
Requires-Dist: pyautogui
